<?xml version="1.0" encoding="UTF-8"?>
<fig id="fig7" orientation="portrait" position="float">
 <label>Figure 7</label>
 <caption>
  <p>(Left) HRTEM images of the twin interfaces and (right) simulations of the inset panels for (
   <italic>a</italic>) the 
   <inline-formula>
    <inline-graphic xlink:href="j-52-01009-efi10.jpg" mimetype="image" mime-subtype="gif" xmlns:xlink="http://www.w3.org/1999/xlink"/>
   </inline-formula> boundary and (
   <italic>b</italic>) the 
   <inline-formula>
    <inline-graphic xlink:href="j-52-01009-efi9.jpg" mimetype="image" mime-subtype="gif" xmlns:xlink="http://www.w3.org/1999/xlink"/>
   </inline-formula> boundary using appropriate models from the supercell approach.
  </p>
 </caption>
 <graphic xlink:href="j-52-01009-fig7" xmlns:xlink="http://www.w3.org/1999/xlink"/>
</fig>
