<?xml version="1.0" encoding="UTF-8"?>
<ref id="advs1381-bib-0026">
 <label>26</label>
 <mixed-citation publication-type="journal" id="advs1381-cit-0026">
  <string-name>
   <given-names>X. Y.</given-names>
   <surname>Wei</surname>
  </string-name>, 
  <string-name>
   <given-names>X. D.</given-names>
   <surname>Wang</surname>
  </string-name>, 
  <string-name>
   <given-names>S. Y.</given-names>
   <surname>Kuang</surname>
  </string-name>, 
  <string-name>
   <given-names>L.</given-names>
   <surname>Su</surname>
  </string-name>, 
  <string-name>
   <given-names>H. Y.</given-names>
   <surname>Li</surname>
  </string-name>, 
  <string-name>
   <given-names>Y.</given-names>
   <surname>Wang</surname>
  </string-name>, 
  <string-name>
   <given-names>C. F.</given-names>
   <surname>Pan</surname>
  </string-name>, 
  <string-name>
   <given-names>Z. L.</given-names>
   <surname>Wang</surname>
  </string-name>, 
  <string-name>
   <given-names>G.</given-names>
   <surname>Zhu</surname>
  </string-name>, 
  <source xml:lang="en">Adv. Mater.</source>
  <year>2016</year>, 
  <volume>28</volume>, 
  <fpage>6656</fpage>.
  <pub-id pub-id-type="pmid">27213998</pub-id>
 </mixed-citation>
</ref>
