<?xml version="1.0" encoding="UTF-8"?>
<results title="frequencies">
 <result title="frequency" word="α-SiB" count="218"/>
 <result title="frequency" word="β-SiB" count="118"/>
 <result title="frequency" word=".()" count="108"/>
 <result title="frequency" word="SiB" count="103"/>
 <result title="frequency" word="Figure" count="68"/>
 <result title="frequency" word="boron" count="56"/>
 <result title="frequency" word="atoms" count="52"/>
 <result title="frequency" word="using" count="39"/>
 <result title="frequency" word="structure" count="38"/>
 <result title="frequency" word="composition" count="37"/>
 <result title="frequency" word="α-B" count="37"/>
 <result title="frequency" word="crystals" count="36"/>
 <result title="frequency" word="formation" count="35"/>
 <result title="frequency" word="Phys." count="33"/>
 <result title="frequency" word="polar" count="32"/>
 <result title="frequency" word="reaction" count="30"/>
 <result title="frequency" word="samples" count="30"/>
 <result title="frequency" word="icosahedral" count="28"/>
 <result title="frequency" word="sample" count="28"/>
 <result title="frequency" word="atom" count="27"/>
 <result title="frequency" word="obtained" count="26"/>
 <result title="frequency" word="°C," count="26"/>
 <result title="frequency" word="Rev." count="25"/>
 <result title="frequency" word="Raman" count="24"/>
 <result title="frequency" word="skeleton," count="24"/>
 <result title="frequency" word="model" count="23"/>
 <result title="frequency" word="respect" count="23"/>
 <result title="frequency" word="synthesis" count="23"/>
 <result title="frequency" word="temperatures" count="22"/>
 <result title="frequency" word="disordered" count="21"/>
 <result title="frequency" word="icosahedra" count="21"/>
 <result title="frequency" word="stable" count="21"/>
 <result title="frequency" word="°C." count="21"/>
 <result title="frequency" word=".–." count="20"/>
 <result title="frequency" word="Chem." count="20"/>
 <result title="frequency" word="analysis" count="20"/>
 <result title="frequency" word="mixtures" count="20"/>
 <result title="frequency" word="phase" count="20"/>
 <result title="frequency" word="{border-style" count="20"/>
 <result title="frequency" word="modes" count="19"/>
 <result title="frequency" word="skeleton" count="19"/>
 <result title="frequency" word="total" count="19"/>
 <result title="frequency" word="./PhysRevB.." count="18"/>
 <result title="frequency" word="Supporting" count="18"/>
 <result title="frequency" word="associated" count="18"/>
 <result title="frequency" word="crystal" count="18"/>
 <result title="frequency" word="electron" count="18"/>
 <result title="frequency" word="ground-state" count="18"/>
 <result title="frequency" word="position" count="18"/>
 <result title="frequency" word="px;}" count="18"/>
 <result title="frequency" word="silicon" count="18"/>
 <result title="frequency" word="#ffffff;}" count="17"/>
 <result title="frequency" word="PXRD" count="17"/>
 <result title="frequency" word="Table" count="17"/>
 <result title="frequency" word="data" count="17"/>
 <result title="frequency" word="pellets" count="17"/>
 <result title="frequency" word="properties" count="17"/>
 <result title="frequency" word="used" count="17"/>
 <result title="frequency" word="p,Si" count="16"/>
 <result title="frequency" word="size" count="16"/>
 <result title="frequency" word="spectrum" count="16"/>
 <result title="frequency" word="high" count="15"/>
 <result title="frequency" word="single" count="15"/>
 <result title="frequency" word="unit" count="15"/>
 <result title="frequency" word="Si/B" count="14"/>
 <result title="frequency" word="Si–B" count="14"/>
 <result title="frequency" word="bonds" count="14"/>
 <result title="frequency" word="disorder" count="14"/>
 <result title="frequency" word="materials" count="14"/>
 <result title="frequency" word="p,B" count="14"/>
 <result title="frequency" word="respectively." count="14"/>
 <result title="frequency" word="shows" count="14"/>
 <result title="frequency" word="(cf." count="13"/>
 <result title="frequency" word="(see" count="13"/>
 <result title="frequency" word="X-ray" count="13"/>
 <result title="frequency" word="bonding" count="13"/>
 <result title="frequency" word="mixture" count="13"/>
 <result title="frequency" word="p–Si" count="13"/>
 <result title="frequency" word="temperature" count="13"/>
 <result title="frequency" word="However," count="12"/>
 <result title="frequency" word="NMR" count="12"/>
 <result title="frequency" word="bulk" count="12"/>
 <result title="frequency" word="density" count="12"/>
 <result title="frequency" word="electron-precise" count="12"/>
 <result title="frequency" word="e–p" count="12"/>
 <result title="frequency" word="mode" count="12"/>
 <result title="frequency" word="parameters" count="12"/>
 <result title="frequency" word="results" count="12"/>
 <result title="frequency" word="rhombohedral" count="12"/>
 <result title="frequency" word="single-crystal" count="12"/>
 <result title="frequency" word="stability" count="12"/>
 <result title="frequency" word="starting" count="12"/>
 <result title="frequency" word="structural" count="12"/>
 <result title="frequency" word="Boron" count="11"/>
 <result title="frequency" word="S);" count="11"/>
 <result title="frequency" word="SEM" count="11"/>
 <result title="frequency" word="atomic" count="11"/>
 <result title="frequency" word="calculated" count="11"/>
 <result title="frequency" word="cell" count="11"/>
 <result title="frequency" word="close" count="11"/>
 <result title="frequency" word="corresponds" count="11"/>
 <result title="frequency" word="decomposition" count="11"/>
 <result title="frequency" word="different" count="11"/>
 <result title="frequency" word="diffraction" count="11"/>
 <result title="frequency" word="distances" count="11"/>
 <result title="frequency" word="elemental" count="11"/>
 <result title="frequency" word="energy" count="11"/>
 <result title="frequency" word="larger" count="11"/>
 <result title="frequency" word="pellet" count="11"/>
 <result title="frequency" word="performed" count="11"/>
 <result title="frequency" word="range" count="11"/>
 <result title="frequency" word="shown" count="11"/>
 <result title="frequency" word="site" count="11"/>
 <result title="frequency" word="&amp;lt;" count="10"/>
 <result title="frequency" word="(i.e.," count="10"/>
 <result title="frequency" word="EDX" count="10"/>
 <result title="frequency" word="MAS" count="10"/>
 <result title="frequency" word="Mater." count="10"/>
 <result title="frequency" word="Si," count="10"/>
 <result title="frequency" word="boron-rich" count="10"/>
 <result title="frequency" word="cluster" count="10"/>
 <result title="frequency" word="compared" count="10"/>
 <result title="frequency" word="distance" count="10"/>
 <result title="frequency" word="included" count="10"/>
 <result title="frequency" word="low" count="10"/>
 <result title="frequency" word="method" count="10"/>
 <result title="frequency" word="observed" count="10"/>
 <result title="frequency" word="patterns" count="10"/>
 <result title="frequency" word="powder" count="10"/>
 <result title="frequency" word="rhomboid" count="10"/>
 <result title="frequency" word="states" count="10"/>
 <result title="frequency" word="thermal" count="10"/>
 <result title="frequency" word="(Figure" count="9"/>
 <result title="frequency" word="./-()-" count="9"/>
 <result title="frequency" word="Magnusson" count="9"/>
 <result title="frequency" word="Si." count="9"/>
 <result title="frequency" word="University" count="9"/>
 <result title="frequency" word="amorphous" count="9"/>
 <result title="frequency" word="atoms," count="9"/>
 <result title="frequency" word="band" count="9"/>
 <result title="frequency" word="binary" count="9"/>
 <result title="frequency" word="carbide" count="9"/>
 <result title="frequency" word="expansion" count="9"/>
 <result title="frequency" word="group" count="9"/>
 <result title="frequency" word="investigations" count="9"/>
 <result title="frequency" word="lower" count="9"/>
 <result title="frequency" word="phonon" count="9"/>
 <result title="frequency" word="placed" count="9"/>
 <result title="frequency" word="reported" count="9"/>
 <result title="frequency" word="sintering" count="9"/>
 <result title="frequency" word="spectra" count="9"/>
 <result title="frequency" word="time," count="9"/>
 <result title="frequency" word="units" count="9"/>
 <result title="frequency" word="vibrational" count="9"/>
 <result title="frequency" word="–.()" count="9"/>
 <result title="frequency" word="(a)" count="8"/>
 <result title="frequency" word="(Å)" count="8"/>
 <result title="frequency" word="Aselage" count="8"/>
 <result title="frequency" word="Brosset" count="8"/>
 <result title="frequency" word="ECIs" count="8"/>
 <result title="frequency" word="Information)." count="8"/>
 <result title="frequency" word="Structural" count="8"/>
 <result title="frequency" word="atoms." count="8"/>
 <result title="frequency" word="average" count="8"/>
 <result title="frequency" word="calculations" count="8"/>
 <result title="frequency" word="conditions" count="8"/>
 <result title="frequency" word="configurational" count="8"/>
 <result title="frequency" word="contrast" count="8"/>
 <result title="frequency" word="crystalline" count="8"/>
 <result title="frequency" word="dumbbell" count="8"/>
 <result title="frequency" word="form" count="8"/>
 <result title="frequency" word="highly" count="8"/>
 <result title="frequency" word="i.e.," count="8"/>
 <result title="frequency" word="interatomic" count="8"/>
 <result title="frequency" word="lattice" count="8"/>
 <result title="frequency" word="length" count="8"/>
 <result title="frequency" word="material" count="8"/>
 <result title="frequency" word="mixed" count="8"/>
 <result title="frequency" word="narrow" count="8"/>
 <result title="frequency" word="ordered" count="8"/>
 <result title="frequency" word="particle" count="8"/>
 <result title="frequency" word="particles" count="8"/>
 <result title="frequency" word="polycrystalline" count="8"/>
 <result title="frequency" word="predicted" count="8"/>
 <result title="frequency" word="presence" count="8"/>
 <result title="frequency" word="px;" count="8"/>
 <result title="frequency" word="p–B" count="8"/>
 <result title="frequency" word="p–p" count="8"/>
 <result title="frequency" word="rate" count="8"/>
 <result title="frequency" word="refined" count="8"/>
 <result title="frequency" word="refinement" count="8"/>
 <result title="frequency" word="solid" count="8"/>
 <result title="frequency" word="thermodynamic" count="8"/>
 <result title="frequency" word="values" count="8"/>
 <result title="frequency" word="various" count="8"/>
 <result title="frequency" word="{font-family" count="8"/>
 <result title="frequency" word="-derived" count="7"/>
 <result title="frequency" word="B–B" count="7"/>
 <result title="frequency" word="Rietveld" count="7"/>
 <result title="frequency" word="SC-XRD" count="7"/>
 <result title="frequency" word="Solid" count="7"/>
 <result title="frequency" word="chemical" count="7"/>
 <result title="frequency" word="configurations" count="7"/>
 <result title="frequency" word="distribution" count="7"/>
 <result title="frequency" word="energies" count="7"/>
 <result title="frequency" word="excess" count="7"/>
 <result title="frequency" word="exo-bond" count="7"/>
 <result title="frequency" word="font-size" count="7"/>
 <result title="frequency" word="high-pressure" count="7"/>
 <result title="frequency" word="icosahedra," count="7"/>
 <result title="frequency" word="icosahedra." count="7"/>
 <result title="frequency" word="icosahedron" count="7"/>
 <result title="frequency" word="nature" count="7"/>
 <result title="frequency" word="neighboring" count="7"/>
 <result title="frequency" word="nonexistent" count="7"/>
 <result title="frequency" word="orthorhombic" count="7"/>
 <result title="frequency" word="pressure" count="7"/>
 <result title="frequency" word="primitive" count="7"/>
 <result title="frequency" word="product" count="7"/>
 <result title="frequency" word="pure" count="7"/>
 <result title="frequency" word="rates" count="7"/>
 <result title="frequency" word="ratios" count="7"/>
 <result title="frequency" word="reactions" count="7"/>
 <result title="frequency" word="ref" count="7"/>
 <result title="frequency" word="set" count="7"/>
 <result title="frequency" word="similar" count="7"/>
 <result title="frequency" word="sizes" count="7"/>
 <result title="frequency" word="slightly" count="7"/>
 <result title="frequency" word="strained" count="7"/>
 <result title="frequency" word="suggests" count="7"/>
 <result title="frequency" word="symmetry" count="7"/>
 <result title="frequency" word="times" count="7"/>
 <result title="frequency" word="./–." count="6"/>
 <result title="frequency" word="ADP" count="6"/>
 <result title="frequency" word="According" count="6"/>
 <result title="frequency" word="Bonding" count="6"/>
 <result title="frequency" word="DFT" count="6"/>
 <result title="frequency" word="Ektarawong" count="6"/>
 <result title="frequency" word="High" count="6"/>
 <result title="frequency" word="Phase" count="6"/>
 <result title="frequency" word="Research" count="6"/>
 <result title="frequency" word="Si-rich" count="6"/>
 <result title="frequency" word="Soc." count="6"/>
 <result title="frequency" word="Structure" count="6"/>
 <result title="frequency" word="Tables" count="6"/>
 <result title="frequency" word="agreement" count="6"/>
 <result title="frequency" word="and," count="6"/>
 <result title="frequency" word="cf." count="6"/>
 <result title="frequency" word="charge" count="6"/>
 <result title="frequency" word="clearly" count="6"/>
 <result title="frequency" word="configuration" count="6"/>
 <result title="frequency" word="considerably" count="6"/>
 <result title="frequency" word="correspond" count="6"/>
 <result title="frequency" word="depicted" count="6"/>
 <result title="frequency" word="determined" count="6"/>
 <result title="frequency" word="double;" count="6"/>
 <result title="frequency" word="dwelling" count="6"/>
 <result title="frequency" word="electronic" count="6"/>
 <result title="frequency" word="employed" count="6"/>
 <result title="frequency" word="exo-bonds" count="6"/>
 <result title="frequency" word="heated" count="6"/>
 <result title="frequency" word="image" count="6"/>
 <result title="frequency" word="important" count="6"/>
 <result title="frequency" word="increased" count="6"/>
 <result title="frequency" word="indicated" count="6"/>
 <result title="frequency" word="location" count="6"/>
 <result title="frequency" word="nano" count="6"/>
 <result title="frequency" word="nano-Si/B" count="6"/>
 <result title="frequency" word="note" count="6"/>
 <result title="frequency" word="number" count="6"/>
 <result title="frequency" word="occupancies" count="6"/>
 <result title="frequency" word="occupancy" count="6"/>
 <result title="frequency" word="optical" count="6"/>
 <result title="frequency" word="phases" count="6"/>
 <result title="frequency" word="principles" count="6"/>
 <result title="frequency" word="products" count="6"/>
 <result title="frequency" word="red" count="6"/>
 <result title="frequency" word="relative" count="6"/>
 <result title="frequency" word="significantly" count="6"/>
 <result title="frequency" word="solids" count="6"/>
 <result title="frequency" word="stretching" count="6"/>
 <result title="frequency" word="studies" count="6"/>
 <result title="frequency" word="subsequently" count="6"/>
 <result title="frequency" word="substitution" count="6"/>
 <result title="frequency" word="thermodynamically" count="6"/>
 <result title="frequency" word="volume" count="6"/>
 <result title="frequency" word="μm." count="6"/>
 <result title="frequency" word="(%)" count="5"/>
 <result title="frequency" word=".()," count="5"/>
 <result title="frequency" word=".()." count="5"/>
 <result title="frequency" word="Alling" count="5"/>
 <result title="frequency" word="Crystal" count="5"/>
 <result title="frequency" word="Emin" count="5"/>
 <result title="frequency" word="Häussermann" count="5"/>
 <result title="frequency" word="Information" count="5"/>
 <result title="frequency" word="Int." count="5"/>
 <result title="frequency" word="Lett." count="5"/>
 <result title="frequency" word="Salvador" count="5"/>
 <result title="frequency" word="Sci." count="5"/>
 <result title="frequency" word="Section" count="5"/>
 <result title="frequency" word="Silicon" count="5"/>
 <result title="frequency" word="Simak" count="5"/>
 <result title="frequency" word="Si–Si" count="5"/>
 <result title="frequency" word="State" count="5"/>
 <result title="frequency" word="Swedish" count="5"/>
 <result title="frequency" word="Synthesis" count="5"/>
 <result title="frequency" word="Thus," count="5"/>
 <result title="frequency" word="appears" count="5"/>
 <result title="frequency" word="application" count="5"/>
 <result title="frequency" word="bands" count="5"/>
 <result title="frequency" word="black" count="5"/>
 <result title="frequency" word="border-color" count="5"/>
 <result title="frequency" word="border-width" count="5"/>
 <result title="frequency" word="chains" count="5"/>
 <result title="frequency" word="clear" count="5"/>
 <result title="frequency" word="closer" count="5"/>
 <result title="frequency" word="collected" count="5"/>
 <result title="frequency" word="composition," count="5"/>
 <result title="frequency" word="conversion" count="5"/>
 <result title="frequency" word="crystals." count="5"/>
 <result title="frequency" word="detailed" count="5"/>
 <result title="frequency" word="established" count="5"/>
 <result title="frequency" word="exo" count="5"/>
 <result title="frequency" word="exo," count="5"/>
 <result title="frequency" word="experiment" count="5"/>
 <result title="frequency" word="experimental" count="5"/>
 <result title="frequency" word="e–B" count="5"/>
 <result title="frequency" word="features" count="5"/>
 <result title="frequency" word="higher" count="5"/>
 <result title="frequency" word="improved" count="5"/>
 <result title="frequency" word="initial" count="5"/>
 <result title="frequency" word="irregularly" count="5"/>
 <result title="frequency" word="large" count="5"/>
 <result title="frequency" word="layers" count="5"/>
 <result title="frequency" word="metal" count="5"/>
 <result title="frequency" word="metastable" count="5"/>
 <result title="frequency" word="microscopy" count="5"/>
 <result title="frequency" word="molar" count="5"/>
 <result title="frequency" word="nano-Si" count="5"/>
 <result title="frequency" word="possible" count="5"/>
 <result title="frequency" word="power" count="5"/>
 <result title="frequency" word="ratio" count="5"/>
 <result title="frequency" word="reflections" count="5"/>
 <result title="frequency" word="relation" count="5"/>
 <result title="frequency" word="represents" count="5"/>
 <result title="frequency" word="seen" count="5"/>
 <result title="frequency" word="semiconductor" count="5"/>
 <result title="frequency" word="signal" count="5"/>
 <result title="frequency" word="significant" count="5"/>
 <result title="frequency" word="solid;" count="5"/>
 <result title="frequency" word="space" count="5"/>
 <result title="frequency" word="split" count="5"/>
 <result title="frequency" word="state" count="5"/>
 <result title="frequency" word="stoichiometric" count="5"/>
 <result title="frequency" word="study" count="5"/>
 <result title="frequency" word="supported" count="5"/>
 <result title="frequency" word="temperature." count="5"/>
 <result title="frequency" word="time" count="5"/>
 <result title="frequency" word="unreacted" count="5"/>
 <result title="frequency" word="{font-style" count="5"/>
 <result title="frequency" word="{font-weight" count="5"/>
 <result title="frequency" word="&amp;gt;" count="4"/>
 <result title="frequency" word="(CE)" count="4"/>
 <result title="frequency" word="(b)" count="4"/>
 <result title="frequency" word="(b)." count="4"/>
 <result title="frequency" word="(obtained" count="4"/>
 <result title="frequency" word="(space" count="4"/>
 <result title="frequency" word="(which" count="4"/>
 <result title="frequency" word="./anie." count="4"/>
 <result title="frequency" word="ACS" count="4"/>
 <result title="frequency" word="Am." count="4"/>
 <result title="frequency" word="Angew." count="4"/>
 <result title="frequency" word="As," count="4"/>
 <result title="frequency" word="Chem.," count="4"/>
 <result title="frequency" word="DOS" count="4"/>
 <result title="frequency" word="Data" count="4"/>
 <result title="frequency" word="Density" count="4"/>
 <result title="frequency" word="Ed." count="4"/>
 <result title="frequency" word="Eds.;" count="4"/>
 <result title="frequency" word="Electronic" count="4"/>
 <result title="frequency" word="Figures" count="4"/>
 <result title="frequency" word="ICSD" count="4"/>
 <result title="frequency" word="Icosahedral" count="4"/>
 <result title="frequency" word="Information." count="4"/>
 <result title="frequency" word="Materials" count="4"/>
 <result title="frequency" word="Model" count="4"/>
 <result title="frequency" word="Nano-Si/B" count="4"/>
 <result title="frequency" word="Si)" count="4"/>
 <result title="frequency" word="Solids" count="4"/>
 <result title="frequency" word="Tallant" count="4"/>
 <result title="frequency" word="according" count="4"/>
 <result title="frequency" word="actually" count="4"/>
 <result title="frequency" word="and/or" count="4"/>
 <result title="frequency" word="approximately" count="4"/>
 <result title="frequency" word="arranged" count="4"/>
 <result title="frequency" word="arrangement" count="4"/>
 <result title="frequency" word="attain" count="4"/>
 <result title="frequency" word="background" count="4"/>
 <result title="frequency" word="based" count="4"/>
 <result title="frequency" word="bold" count="4"/>
 <result title="frequency" word="bonds." count="4"/>
 <result title="frequency" word="borides" count="4"/>
 <result title="frequency" word="broad" count="4"/>
 <result title="frequency" word="comparatively" count="4"/>
 <result title="frequency" word="completely" count="4"/>
 <result title="frequency" word="composed" count="4"/>
 <result title="frequency" word="composition." count="4"/>
 <result title="frequency" word="compositional" count="4"/>
 <result title="frequency" word="compositions" count="4"/>
 <result title="frequency" word="compositions," count="4"/>
 <result title="frequency" word="connecting" count="4"/>
 <result title="frequency" word="considered" count="4"/>
 <result title="frequency" word="contrast," count="4"/>
 <result title="frequency" word="control" count="4"/>
 <result title="frequency" word="cooled" count="4"/>
 <result title="frequency" word="correlation" count="4"/>
 <result title="frequency" word="count" count="4"/>
 <result title="frequency" word="courier;" count="4"/>
 <result title="frequency" word="crystallized" count="4"/>
 <result title="frequency" word="derived" count="4"/>
 <result title="frequency" word="described" count="4"/>
 <result title="frequency" word="detector" count="4"/>
 <result title="frequency" word="deviations" count="4"/>
 <result title="frequency" word="device" count="4"/>
 <result title="frequency" word="difference" count="4"/>
 <result title="frequency" word="discussed" count="4"/>
 <result title="frequency" word="displacement" count="4"/>
 <result title="frequency" word="does" count="4"/>
 <result title="frequency" word="dumbbells." count="4"/>
 <result title="frequency" word="e.g.," count="4"/>
 <result title="frequency" word="e/Å" count="4"/>
 <result title="frequency" word="electrons" count="4"/>
 <result title="frequency" word="em;" count="4"/>
 <result title="frequency" word="enthalpy" count="4"/>
 <result title="frequency" word="equal" count="4"/>
 <result title="frequency" word="essentially" count="4"/>
 <result title="frequency" word="estimated" count="4"/>
 <result title="frequency" word="expansion." count="4"/>
 <result title="frequency" word="expected" count="4"/>
 <result title="frequency" word="experiments" count="4"/>
 <result title="frequency" word="expressed" count="4"/>
 <result title="frequency" word="final" count="4"/>
 <result title="frequency" word="following," count="4"/>
 <result title="frequency" word="free" count="4"/>
 <result title="frequency" word="function" count="4"/>
 <result title="frequency" word="gaps" count="4"/>
 <result title="frequency" word="ground" count="4"/>
 <result title="frequency" word="high-resolution" count="4"/>
 <result title="frequency" word="homogeneity" count="4"/>
 <result title="frequency" word="implies" count="4"/>
 <result title="frequency" word="initio" count="4"/>
 <result title="frequency" word="inset" count="4"/>
 <result title="frequency" word="inside" count="4"/>
 <result title="frequency" word="instrument" count="4"/>
 <result title="frequency" word="interesting" count="4"/>
 <result title="frequency" word="intericosahedral" count="4"/>
 <result title="frequency" word="kinetics" count="4"/>
 <result title="frequency" word="liquid" count="4"/>
 <result title="frequency" word="located" count="4"/>
 <result title="frequency" word="long" count="4"/>
 <result title="frequency" word="materials." count="4"/>
 <result title="frequency" word="molten" count="4"/>
 <result title="frequency" word="negative" count="4"/>
 <result title="frequency" word="occur" count="4"/>
 <result title="frequency" word="optimum" count="4"/>
 <result title="frequency" word="pDOS" count="4"/>
 <result title="frequency" word="package" count="4"/>
 <result title="frequency" word="pair" count="4"/>
 <result title="frequency" word="plane" count="4"/>
 <result title="frequency" word="plasma" count="4"/>
 <result title="frequency" word="possibly" count="4"/>
 <result title="frequency" word="pressed" count="4"/>
 <result title="frequency" word="pressures" count="4"/>
 <result title="frequency" word="probability" count="4"/>
 <result title="frequency" word="pt;}" count="4"/>
 <result title="frequency" word="reasonable" count="4"/>
 <result title="frequency" word="recently" count="4"/>
 <result title="frequency" word="reduced" count="4"/>
 <result title="frequency" word="removed" count="4"/>
 <result title="frequency" word="reports" count="4"/>
 <result title="frequency" word="represent" count="4"/>
 <result title="frequency" word="resolution" count="4"/>
 <result title="frequency" word="result" count="4"/>
 <result title="frequency" word="ring" count="4"/>
 <result title="frequency" word="room" count="4"/>
 <result title="frequency" word="sample," count="4"/>
 <result title="frequency" word="sample." count="4"/>
 <result title="frequency" word="samples." count="4"/>
 <result title="frequency" word="scanning" count="4"/>
 <result title="frequency" word="sharp" count="4"/>
 <result title="frequency" word="showed" count="4"/>
 <result title="frequency" word="sintered" count="4"/>
 <result title="frequency" word="site." count="4"/>
 <result title="frequency" word="sites" count="4"/>
 <result title="frequency" word="sites." count="4"/>
 <result title="frequency" word="smaller" count="4"/>
 <result title="frequency" word="spark" count="4"/>
 <result title="frequency" word="specimens" count="4"/>
 <result title="frequency" word="spectroscopy" count="4"/>
 <result title="frequency" word="structure," count="4"/>
 <result title="frequency" word="structures" count="4"/>
 <result title="frequency" word="sum" count="4"/>
 <result title="frequency" word="support" count="4"/>
 <result title="frequency" word="system." count="4"/>
 <result title="frequency" word="theoretical" count="4"/>
 <result title="frequency" word="unstable" count="4"/>
 <result title="frequency" word="work" count="4"/>
 <result title="frequency" word="yield" count="4"/>
 <result title="frequency" word="°C)" count="4"/>
 <result title="frequency" word="°C)." count="4"/>
 <result title="frequency" word="Å)." count="4"/>
</results>
