<?xml version="1.0" encoding="UTF-8"?>
<results title="frequencies">
 <result title="frequency" word="water" count="54"/>
 <result title="frequency" word="molecules" count="36"/>
 <result title="frequency" word="type" count="31"/>
 <result title="frequency" word="distribution" count="30"/>
 <result title="frequency" word="Chem." count="29"/>
 <result title="frequency" word="Phys." count="28"/>
 <result title="frequency" word="crystal" count="28"/>
 <result title="frequency" word="ions" count="28"/>
 <result title="frequency" word="Figure" count="27"/>
 <result title="frequency" word="hydration" count="24"/>
 <result title="frequency" word="Dynamics" count="22"/>
 <result title="frequency" word="NaCl" count="21"/>
 <result title="frequency" word="interface" count="20"/>
 <result title="frequency" word="{border-style" count="20"/>
 <result title="frequency" word="Molecular" count="19"/>
 <result title="frequency" word="Water" count="19"/>
 <result title="frequency" word="structure" count="19"/>
 <result title="frequency" word="px;}" count="18"/>
 <result title="frequency" word="#ffffff;}" count="17"/>
 <result title="frequency" word="Interface" count="16"/>
 <result title="frequency" word="FHS" count="15"/>
 <result title="frequency" word="solution" count="15"/>
 <result title="frequency" word="peak" count="13"/>
 <result title="frequency" word="Structure" count="12"/>
 <result title="frequency" word="number" count="12"/>
 <result title="frequency" word="RDF" count="11"/>
 <result title="frequency" word="Surface" count="11"/>
 <result title="frequency" word="shell" count="11"/>
 <result title="frequency" word="Ions" count="10"/>
 <result title="frequency" word="coordinate" count="10"/>
 <result title="frequency" word="dipole" count="10"/>
 <result title="frequency" word="layer" count="10"/>
 <result title="frequency" word="respectively." count="10"/>
 <result title="frequency" word="shown" count="10"/>
 <result title="frequency" word="Aqueous" count="9"/>
 <result title="frequency" word="Ion" count="9"/>
 <result title="frequency" word="Simulations" count="9"/>
 <result title="frequency" word="cos(γ)" count="9"/>
 <result title="frequency" word="position" count="9"/>
 <result title="frequency" word="surface" count="9"/>
 <result title="frequency" word="However," count="8"/>
 <result title="frequency" word="cos(α)" count="8"/>
 <result title="frequency" word="density" count="8"/>
 <result title="frequency" word="ionic" count="8"/>
 <result title="frequency" word="ions," count="8"/>
 <result title="frequency" word="ions." count="8"/>
 <result title="frequency" word="lattice" count="8"/>
 <result title="frequency" word="orientation" count="8"/>
 <result title="frequency" word="px;" count="8"/>
 <result title="frequency" word="{font-family" count="8"/>
 <result title="frequency" word="(a)" count="7"/>
 <result title="frequency" word="Adsorption" count="7"/>
 <result title="frequency" word="Hydration" count="7"/>
 <result title="frequency" word="Langmuir" count="7"/>
 <result title="frequency" word="approaching" count="7"/>
 <result title="frequency" word="cos(φ)" count="7"/>
 <result title="frequency" word="defined" count="7"/>
 <result title="frequency" word="different" count="7"/>
 <result title="frequency" word="effect" count="7"/>
 <result title="frequency" word="font-size" count="7"/>
 <result title="frequency" word="interface," count="7"/>
 <result title="frequency" word="ion" count="7"/>
 <result title="frequency" word="layer," count="7"/>
 <result title="frequency" word="simulation" count="7"/>
 <result title="frequency" word="Alkali" count="6"/>
 <result title="frequency" word="Dissolution" count="6"/>
 <result title="frequency" word="Distribution" count="6"/>
 <result title="frequency" word="FHS." count="6"/>
 <result title="frequency" word="Salt" count="6"/>
 <result title="frequency" word="concentration" count="6"/>
 <result title="frequency" word="coordination" count="6"/>
 <result title="frequency" word="counter" count="6"/>
 <result title="frequency" word="double;" count="6"/>
 <result title="frequency" word="epitaxial" count="6"/>
 <result title="frequency" word="local" count="6"/>
 <result title="frequency" word="molecules." count="6"/>
 <result title="frequency" word="namely," count="6"/>
 <result title="frequency" word="near" count="6"/>
 <result title="frequency" word="nearest" count="6"/>
 <result title="frequency" word="physical" count="6"/>
 <result title="frequency" word="tendency" count="6"/>
 <result title="frequency" word="unit" count="6"/>
 <result title="frequency" word="./acs.jpcc.b" count="5"/>
 <result title="frequency" word="Commun." count="5"/>
 <result title="frequency" word="Fenter" count="5"/>
 <result title="frequency" word="Interfacial" count="5"/>
 <result title="frequency" word="Liu" count="5"/>
 <result title="frequency" word="Nat." count="5"/>
 <result title="frequency" word="SLI" count="5"/>
 <result title="frequency" word="Sci." count="5"/>
 <result title="frequency" word="Solution" count="5"/>
 <result title="frequency" word="Solutions" count="5"/>
 <result title="frequency" word="Study" count="5"/>
 <result title="frequency" word="border-color" count="5"/>
 <result title="frequency" word="border-width" count="5"/>
 <result title="frequency" word="central" count="5"/>
 <result title="frequency" word="dash" count="5"/>
 <result title="frequency" word="direction" count="5"/>
 <result title="frequency" word="dynamics" count="5"/>
 <result title="frequency" word="layer." count="5"/>
 <result title="frequency" word="molecular" count="5"/>
 <result title="frequency" word="molecules," count="5"/>
 <result title="frequency" word="ordering" count="5"/>
 <result title="frequency" word="perpendicular" count="5"/>
 <result title="frequency" word="radius" count="5"/>
 <result title="frequency" word="solid;" count="5"/>
 <result title="frequency" word="solid–liquid" count="5"/>
 <result title="frequency" word="solution." count="5"/>
 <result title="frequency" word="{font-style" count="5"/>
 <result title="frequency" word="{font-weight" count="5"/>
 <result title="frequency" word="–-O" count="5"/>
 <result title="frequency" word="./." count="4"/>
 <result title="frequency" word="Am." count="4"/>
 <result title="frequency" word="Halide" count="4"/>
 <result title="frequency" word="Kerisit" count="4"/>
 <result title="frequency" word="Kobayashi" count="4"/>
 <result title="frequency" word="Michaelides" count="4"/>
 <result title="frequency" word="Miller" count="4"/>
 <result title="frequency" word="Molecules" count="4"/>
 <result title="frequency" word="Muscovite" count="4"/>
 <result title="frequency" word="Role" count="4"/>
 <result title="frequency" word="Simulation" count="4"/>
 <result title="frequency" word="Soc." count="4"/>
 <result title="frequency" word="Spijker" count="4"/>
 <result title="frequency" word="Surfaces" count="4"/>
 <result title="frequency" word="Table" count="4"/>
 <result title="frequency" word="[]," count="4"/>
 <result title="frequency" word="angle" count="4"/>
 <result title="frequency" word="angles" count="4"/>
 <result title="frequency" word="bin," count="4"/>
 <result title="frequency" word="bold" count="4"/>
 <result title="frequency" word="coordinating" count="4"/>
 <result title="frequency" word="courier;" count="4"/>
 <result title="frequency" word="denotes" count="4"/>
 <result title="frequency" word="em;" count="4"/>
 <result title="frequency" word="environment" count="4"/>
 <result title="frequency" word="experimental" count="4"/>
 <result title="frequency" word="ideal" count="4"/>
 <result title="frequency" word="important" count="4"/>
 <result title="frequency" word="interface." count="4"/>
 <result title="frequency" word="interfaces." count="4"/>
 <result title="frequency" word="ion-oxygen" count="4"/>
 <result title="frequency" word="line" count="4"/>
 <result title="frequency" word="model" count="4"/>
 <result title="frequency" word="obviously" count="4"/>
 <result title="frequency" word="ordered" count="4"/>
 <result title="frequency" word="prefers" count="4"/>
 <result title="frequency" word="previous" count="4"/>
 <result title="frequency" word="pt;}" count="4"/>
 <result title="frequency" word="results" count="4"/>
 <result title="frequency" word="structure," count="4"/>
 <result title="frequency" word="surface." count="4"/>
 <result title="frequency" word="that," count="4"/>
 <result title="frequency" word="time" count="4"/>
 <result title="frequency" word="vector" count="4"/>
</results>
