<?xml version="1.0" encoding="UTF-8"?>
<abstract abstract-type="graphical">
 <p>
  <bold>How to Cat</bold>: The experimental and theoretical topological analysis of the electron density distribution in Co
  <sub>3</sub>(PO
  <sub>4</sub>)
  <sub>2</sub> identified the (011) face to be best suited for catalysis. Fivefold‐coordinated Co ions in close proximity to advantageously oriented electron‐depletion sites suit the reactant's oxygen lone pairs most for chemisorption and heterogeneous C−H activation.
  <boxed-text position="anchor" content-type="graphic" orientation="portrait">
   <graphic xlink:href="CHEM-25-15786-g009.jpg" position="anchor" id="nlm-graphic-1" orientation="portrait" xmlns:xlink="http://www.w3.org/1999/xlink"/>
  </boxed-text>
 </p>
</abstract>
