<?xml version="1.0" encoding="UTF-8"?>
<fig id="micromachines-10-00181-f012" orientation="portrait" position="float">
 <label>Figure 12</label>
 <caption>
  <p>Comparison of natural frequencies of the central-supported DRG at different geometry parameters obtained by the simulation and calculation: (
   <bold>a</bold>) natural frequencies of the simulation and calculation results and (
   <bold>b</bold>) the relative error of the natural frequencies obtained by the two methods.
  </p>
 </caption>
 <graphic xlink:href="micromachines-10-00181-g012" xmlns:xlink="http://www.w3.org/1999/xlink"/>
</fig>
