<?xml version="1.0" encoding="UTF-8"?>
<table-wrap id="tbl5" position="float">
 <label>Table 5</label>
 <caption>
  <title>Fractional Coordinates, Equivalent Isotropic ADP Values 
   <italic>U</italic>
   <sub>eq</sub>, and Site Occupancy Factors for α-SiB
   <sub>3–
    <italic>x</italic>
   </sub>, Model 
   <bold>4</bold> [Space Group 
   <italic>R</italic>3̅
   <italic>m</italic>, 
   <italic>a</italic> = 6.3282(1), 
   <italic>c</italic> = 12.7283(3)]
  </title>
 </caption>
 <table frame="hsides" rules="groups" border="0">
  <colgroup>
   <col align="left"/>
   <col align="left"/>
   <col align="left"/>
   <col align="left"/>
   <col align="char" char="."/>
   <col align="char" char="."/>
   <col align="char" char="."/>
  </colgroup>
  <thead>
   <tr>
    <th style="border:none;" align="center">atom</th>
    <th style="border:none;" align="center">site</th>
    <th style="border:none;" align="center">
     <italic>x</italic>/
     <italic>a</italic>
    </th>
    <th style="border:none;" align="center">
     <italic>y</italic>/
     <italic>b</italic>
    </th>
    <th style="border:none;" align="center" char=".">
     <italic>z</italic>/
     <italic>c</italic>
    </th>
    <th style="border:none;" align="center" char=".">
     <italic>U</italic>
     <sub>eq</sub> (Å 
     <sup>2</sup>)
    </th>
    <th style="border:none;" align="center" char=".">s.o.f.</th>
   </tr>
  </thead>
  <tbody>
   <tr>
    <td style="border:none;" align="left">B
     <sup>e</sup>
    </td>
    <td style="border:none;" align="left">18h</td>
    <td style="border:none;" align="left">0.15673(6)</td>
    <td style="border:none;" align="left">0.31345(12)</td>
    <td style="border:none;" align="char" char=".">0.02634(7)</td>
    <td style="border:none;" align="char" char=".">0.01142(6)</td>
    <td style="border:none;" align="char" char=".">1.0</td>
   </tr>
   <tr>
    <td style="border:none;" align="left">B
     <sup>p,B</sup>
    </td>
    <td style="border:none;" align="left">18h</td>
    <td style="border:none;" align="left">0.1124(3)</td>
    <td style="border:none;" align="left">–0.1124(3)</td>
    <td style="border:none;" align="char" char=".">0.8849(3)</td>
    <td style="border:none;" align="char" char=".">0.0092(2)</td>
    <td style="border:none;" align="char" char=".">0.374(4)</td>
   </tr>
   <tr>
    <td style="border:none;" align="left">B
     <sup>p,Si</sup>
    </td>
    <td style="border:none;" align="left">18h</td>
    <td style="border:none;" align="left">0.0932(2)</td>
    <td style="border:none;" align="left">–0.0932(2)</td>
    <td style="border:none;" align="char" char=".">0.9009(2)</td>
    <td style="border:none;" align="char" char=".">0.0092(2)</td>
    <td style="border:none;" align="char" char=".">0.319(4)</td>
   </tr>
   <tr>
    <td style="border:none;" align="left">Si
     <sup>p</sup>
    </td>
    <td style="border:none;" align="left">18h</td>
    <td style="border:none;" align="left">0.1138(1)</td>
    <td style="border:none;" align="left">0.1138(1)</td>
    <td style="border:none;" align="char" char=".">0.87447(8)</td>
    <td style="border:none;" align="char" char=".">0.0115(1)</td>
    <td style="border:none;" align="char" char=".">0.308(1)</td>
   </tr>
   <tr>
    <td style="border:none;" align="left">Si
     <sup>d</sup>
    </td>
    <td style="border:none;" align="left">6c</td>
    <td style="border:none;" align="left">0</td>
    <td style="border:none;" align="left">0</td>
    <td style="border:none;" align="char" char=".">0.40518(3)</td>
    <td style="border:none;" align="char" char=".">0.00678(7)</td>
    <td style="border:none;" align="char" char=".">1.0</td>
   </tr>
  </tbody>
 </table>
</table-wrap>
