<?xml version="1.0" encoding="UTF-8"?>
<ref id="chem201902303-bib-0001a">
 <label>1a</label>
 <mixed-citation publication-type="book" id="chem201902303-cit-0002">
  <string-name>
   <given-names>B.</given-names>
   <surname>Cornils</surname>
  </string-name>, 
  <string-name>
   <given-names>W. A.</given-names>
   <surname>Herrmann</surname>
  </string-name>, 
  <source xml:lang="en">Applied Homogenous Catalysis with Organometallic Compounds</source>, 
  <publisher-name>VCH</publisher-name>, 
  <publisher-loc>Weinheim</publisher-loc>, 
  <year>1996</year>;
 </mixed-citation>
</ref>
