<?xml version="1.0" encoding="UTF-8"?>
<ref id="chem201902303-bib-0034">
 <label>34</label>
 <mixed-citation publication-type="journal" id="chem201902303-cit-0054">
  <string-name>
   <given-names>T.</given-names>
   <surname>Schulz</surname>
  </string-name>, 
  <string-name>
   <given-names>K.</given-names>
   <surname>Meindl</surname>
  </string-name>, 
  <string-name>
   <given-names>D.</given-names>
   <surname>Leusser</surname>
  </string-name>, 
  <string-name>
   <given-names>D.</given-names>
   <surname>Stern</surname>
  </string-name>, 
  <string-name>
   <given-names>J.</given-names>
   <surname>Graf</surname>
  </string-name>, 
  <string-name>
   <given-names>C.</given-names>
   <surname>Michaelsen</surname>
  </string-name>, 
  <string-name>
   <given-names>M.</given-names>
   <surname>Ruf</surname>
  </string-name>, 
  <string-name>
   <given-names>G. M.</given-names>
   <surname>Sheldrick</surname>
  </string-name>, 
  <string-name>
   <given-names>D.</given-names>
   <surname>Stalke</surname>
  </string-name>, 
  <source xml:lang="en">J. Appl. Crystallogr.</source>
  <year>2009</year>, 
  <volume>42</volume>, 
  <fpage>885</fpage>.
 </mixed-citation>
</ref>
