<?xml version="1.0" encoding="UTF-8"?>
<results title="frequencies">
 <result title="frequency" word="perovskite" count="76"/>
 <result title="frequency" word="CsPbBr" count="69"/>
 <result title="frequency" word="YCl" count="55"/>
 <result title="frequency" word="(:)" count="52"/>
 <result title="frequency" word="film" count="52"/>
 <result title="frequency" word="films" count="41"/>
 <result title="frequency" word="Fig." count="39"/>
 <result title="frequency" word="PEACl:CsPbBr" count="31"/>
 <result title="frequency" word="PLQE" count="26"/>
 <result title="frequency" word=":PEACl" count="24"/>
 <result title="frequency" word="diodes" count="24"/>
 <result title="frequency" word="light-emitting" count="23"/>
 <result title="frequency" word=".Cl" count="21"/>
 <result title="frequency" word="sky-blue" count="21"/>
 <result title="frequency" word="Nat." count="20"/>
 <result title="frequency" word="efficiency" count="20"/>
 <result title="frequency" word="shown" count="20"/>
 <result title="frequency" word="{border-style" count="20"/>
 <result title="frequency" word="Supplementary" count="18"/>
 <result title="frequency" word="perovskites" count="18"/>
 <result title="frequency" word="px;}" count="18"/>
 <result title="frequency" word="#ffffff;}" count="17"/>
 <result title="frequency" word="PeLEDs" count="17"/>
 <result title="frequency" word="layered" count="17"/>
 <result title="frequency" word="phase" count="17"/>
 <result title="frequency" word="device" count="16"/>
 <result title="frequency" word="energy" count="16"/>
 <result title="frequency" word=" nm" count="16"/>
 <result title="frequency" word="different" count="15"/>
 <result title="frequency" word="peak" count="15"/>
 <result title="frequency" word="quantum" count="15"/>
 <result title="frequency" word="yttrium" count="15"/>
 <result title="frequency" word="blue" count="14"/>
 <result title="frequency" word="emission" count="14"/>
 <result title="frequency" word="solution" count="14"/>
 <result title="frequency" word="./s---" count="13"/>
 <result title="frequency" word="EQE" count="13"/>
 <result title="frequency" word="ratios" count="13"/>
 <result title="frequency" word="PEACl" count="12"/>
 <result title="frequency" word="crystal" count="12"/>
 <result title="frequency" word="devices" count="12"/>
 <result title="frequency" word="ion" count="12"/>
 <result title="frequency" word="shows" count="12"/>
 <result title="frequency" word="Commun." count="11"/>
 <result title="frequency" word="efficient" count="11"/>
 <result title="frequency" word="photoluminescence" count="11"/>
 <result title="frequency" word="ratio" count="11"/>
 <result title="frequency" word="spectra" count="11"/>
 <result title="frequency" word="study" count="11"/>
 <result title="frequency" word="using" count="11"/>
 <result title="frequency" word="Mater." count="10"/>
 <result title="frequency" word="PeLED" count="10"/>
 <result title="frequency" word="Y/Pb" count="10"/>
 <result title="frequency" word="halide" count="10"/>
 <result title="frequency" word="light" count="10"/>
 <result title="frequency" word=".%," count="9"/>
 <result title="frequency" word="Nature" count="9"/>
 <result title="frequency" word="Perovskite" count="9"/>
 <result title="frequency" word="XRD" count="9"/>
 <result title="frequency" word="charge" count="9"/>
 <result title="frequency" word="density" count="9"/>
 <result title="frequency" word="films." count="9"/>
 <result title="frequency" word="lead" count="9"/>
 <result title="frequency" word="measurement" count="9"/>
 <result title="frequency" word="migration" count="9"/>
 <result title="frequency" word="n = " count="9"/>
 <result title="frequency" word="performed" count="9"/>
 <result title="frequency" word="spectrum" count="9"/>
 <result title="frequency" word="stability" count="9"/>
 <result title="frequency" word="Energy" count="8"/>
 <result title="frequency" word="Photonics" count="8"/>
 <result title="frequency" word="activation" count="8"/>
 <result title="frequency" word="based" count="8"/>
 <result title="frequency" word="composition" count="8"/>
 <result title="frequency" word="px;" count="8"/>
 <result title="frequency" word="respectively." count="8"/>
 <result title="frequency" word="significantly" count="8"/>
 <result title="frequency" word="surface" count="8"/>
 <result title="frequency" word="used" count="8"/>
 <result title="frequency" word="{font-family" count="8"/>
 <result title="frequency" word=". eV" count="7"/>
 <result title="frequency" word="Wang" count="7"/>
 <result title="frequency" word="conducted" count="7"/>
 <result title="frequency" word="enhancement" count="7"/>
 <result title="frequency" word="films," count="7"/>
 <result title="frequency" word="font-size" count="7"/>
 <result title="frequency" word="grain" count="7"/>
 <result title="frequency" word="higher" count="7"/>
 <result title="frequency" word="incorporation" count="7"/>
 <result title="frequency" word="ions" count="7"/>
 <result title="frequency" word="laser" count="7"/>
 <result title="frequency" word="luminance" count="7"/>
 <result title="frequency" word="samples" count="7"/>
 <result title="frequency" word="segregation" count="7"/>
 <result title="frequency" word="single" count="7"/>
 <result title="frequency" word="temperature" count="7"/>
 <result title="frequency" word="Adv." count="6"/>
 <result title="frequency" word="Chem." count="6"/>
 <result title="frequency" word="Efficient" count="6"/>
 <result title="frequency" word="adding" count="6"/>
 <result title="frequency" word="crystals" count="6"/>
 <result title="frequency" word="curves" count="6"/>
 <result title="frequency" word="double;" count="6"/>
 <result title="frequency" word="efficiencies" count="6"/>
 <result title="frequency" word="electron–phonon" count="6"/>
 <result title="frequency" word="fabricated" count="6"/>
 <result title="frequency" word="film." count="6"/>
 <result title="frequency" word="green" count="6"/>
 <result title="frequency" word="hybrid" count="6"/>
 <result title="frequency" word="increase" count="6"/>
 <result title="frequency" word="intensity" count="6"/>
 <result title="frequency" word="measured" count="6"/>
 <result title="frequency" word="measurement." count="6"/>
 <result title="frequency" word="method" count="6"/>
 <result title="frequency" word="mixed" count="6"/>
 <result title="frequency" word="perovskites," count="6"/>
 <result title="frequency" word="recombination" count="6"/>
 <result title="frequency" word="reported" count="6"/>
 <result title="frequency" word="stable" count="6"/>
 <result title="frequency" word="substrates" count="6"/>
 <result title="frequency" word="(Fig." count="5"/>
 <result title="frequency" word="PLQEs" count="5"/>
 <result title="frequency" word="Photoluminescence" count="5"/>
 <result title="frequency" word="Phys." count="5"/>
 <result title="frequency" word="Yang" count="5"/>
 <result title="frequency" word="absorption" count="5"/>
 <result title="frequency" word="bandgap" count="5"/>
 <result title="frequency" word="border-color" count="5"/>
 <result title="frequency" word="border-width" count="5"/>
 <result title="frequency" word="current" count="5"/>
 <result title="frequency" word="distribution" count="5"/>
 <result title="frequency" word="growth" count="5"/>
 <result title="frequency" word="http://orcid.org/---" count="5"/>
 <result title="frequency" word="increased" count="5"/>
 <result title="frequency" word="increases" count="5"/>
 <result title="frequency" word="interaction" count="5"/>
 <result title="frequency" word="low" count="5"/>
 <result title="frequency" word="peaks" count="5"/>
 <result title="frequency" word="phases" count="5"/>
 <result title="frequency" word="precursor" count="5"/>
 <result title="frequency" word="prepared" count="5"/>
 <result title="frequency" word="solid;" count="5"/>
 <result title="frequency" word="studied" count="5"/>
 <result title="frequency" word="surfaces" count="5"/>
 <result title="frequency" word="{font-style" count="5"/>
 <result title="frequency" word="{font-weight" count="5"/>
 <result title="frequency" word=" cd m" count="5"/>
 <result title="frequency" word="(.," count="4"/>
 <result title="frequency" word="(Supplementary" count="4"/>
 <result title="frequency" word=":PEACl:%YCl" count="4"/>
 <result title="frequency" word="ACS" count="4"/>
 <result title="frequency" word="Adding" count="4"/>
 <result title="frequency" word="CIE" count="4"/>
 <result title="frequency" word="Center" count="4"/>
 <result title="frequency" word="Commons" count="4"/>
 <result title="frequency" word="Creative" count="4"/>
 <result title="frequency" word="EQEs" count="4"/>
 <result title="frequency" word="Figure" count="4"/>
 <result title="frequency" word="Lett." count="4"/>
 <result title="frequency" word="Lin" count="4"/>
 <result title="frequency" word="Science" count="4"/>
 <result title="frequency" word="University" count="4"/>
 <result title="frequency" word="X-ray" count="4"/>
 <result title="frequency" word="XPS" count="4"/>
 <result title="frequency" word="[]," count="4"/>
 <result title="frequency" word="\right)" count="4"/>
 <result title="frequency" word="bias" count="4"/>
 <result title="frequency" word="bold" count="4"/>
 <result title="frequency" word="calculations" count="4"/>
 <result title="frequency" word="calibration" count="4"/>
 <result title="frequency" word="chloride" count="4"/>
 <result title="frequency" word="close" count="4"/>
 <result title="frequency" word="concentration" count="4"/>
 <result title="frequency" word="conduction" count="4"/>
 <result title="frequency" word="conductivity" count="4"/>
 <result title="frequency" word="corresponding" count="4"/>
 <result title="frequency" word="coupling" count="4"/>
 <result title="frequency" word="courier;" count="4"/>
 <result title="frequency" word="data" count="4"/>
 <result title="frequency" word="diffraction" count="4"/>
 <result title="frequency" word="em;" count="4"/>
 <result title="frequency" word="enhanced" count="4"/>
 <result title="frequency" word="enhances" count="4"/>
 <result title="frequency" word="function" count="4"/>
 <result title="frequency" word="glass" count="4"/>
 <result title="frequency" word="gradient" count="4"/>
 <result title="frequency" word="grid.." count="4"/>
 <result title="frequency" word="high" count="4"/>
 <result title="frequency" word="improved" count="4"/>
 <result title="frequency" word="information" count="4"/>
 <result title="frequency" word="inorganic" count="4"/>
 <result title="frequency" word="lower" count="4"/>
 <result title="frequency" word="material" count="4"/>
 <result title="frequency" word="materials" count="4"/>
 <result title="frequency" word="maximum" count="4"/>
 <result title="frequency" word="mixing" count="4"/>
 <result title="frequency" word="previous" count="4"/>
 <result title="frequency" word="probe" count="4"/>
 <result title="frequency" word="pt;}" count="4"/>
 <result title="frequency" word="radiative" count="4"/>
 <result title="frequency" word="red" count="4"/>
 <result title="frequency" word="reduced" count="4"/>
 <result title="frequency" word="results" count="4"/>
 <result title="frequency" word="room" count="4"/>
 <result title="frequency" word="sample" count="4"/>
 <result title="frequency" word="support" count="4"/>
 <result title="frequency" word="system." count="4"/>
 <result title="frequency" word=" min." count="4"/>
</results>
