<?xml version="1.0" encoding="UTF-8"?>
<table-wrap position="float" id="t0010">
 <label>Table 2</label>
 <caption>
  <p>Simulated brucite (s.g. 
   <inline-formula>
    <math id="M13" altimg="si0002.gif" overflow="scroll">
     <mrow>
      <mi>P</mi>
      <mover accent="true">
       <mn>3</mn>
       <mo>¯</mo>
      </mover>
     </mrow>
    </math>
   </inline-formula>) lattice parameters, unit cell volume, density and internal coordinates of each irreducible atom at different hydrostatic compression values.
  </p>
 </caption>
 <alt-text id="at0010">Table 2</alt-text>
 <table frame="hsides" rules="groups">
  <thead>
   <tr>
    <th>
     <bold>Model</bold>
    </th>
    <th>
     <bold>P01</bold>
    </th>
    <th>
     <bold>P02</bold>
    </th>
    <th>
     <bold>P03</bold>
    </th>
    <th>
     <bold>P00</bold>
    </th>
    <th>
     <bold>P04</bold>
    </th>
    <th>
     <bold>P05</bold>
    </th>
    <th>
     <bold>P06</bold>
    </th>
    <th>
     <bold>P07</bold>
    </th>
    <th>
     <bold>P08</bold>
    </th>
    <th>
     <bold>P09</bold>
    </th>
    <th>
     <bold>P10</bold>
    </th>
   </tr>
  </thead>
  <tbody>
   <tr>
    <td>
     <italic>P (GPa)</italic>
    </td>
    <td>−
     <italic>1.73</italic>
    </td>
    <td>−
     <italic>1.37</italic>
    </td>
    <td>−
     <italic>0.63</italic>
    </td>
    <td>−
     <italic>0.04</italic>
    </td>
    <td>
     <italic>0.48</italic>
    </td>
    <td>
     <italic>1.94</italic>
    </td>
    <td>
     <italic>3.75</italic>
    </td>
    <td>
     <italic>5.87</italic>
    </td>
    <td>
     <italic>8.30</italic>
    </td>
    <td>
     <italic>11.03</italic>
    </td>
    <td>
     <italic>14.00</italic>
    </td>
   </tr>
   <tr>
    <td>
     <italic>a (Å)</italic>
    </td>
    <td>5.457850</td>
    <td>5.448528</td>
    <td>5.431555</td>
    <td>5.419010</td>
    <td>5.410109</td>
    <td>5.383694</td>
    <td>5.354487</td>
    <td>5.323469</td>
    <td>5.291050</td>
    <td>5.257357</td>
    <td>5.223264</td>
   </tr>
   <tr>
    <td>
     <italic>a/</italic>√
     <italic>3 (Å)</italic>
    </td>
    <td>3.151091</td>
    <td>3.145709</td>
    <td>3.135910</td>
    <td>3.128667</td>
    <td>3.123528</td>
    <td>3.108277</td>
    <td>3.091415</td>
    <td>3.073506</td>
    <td>3.054789</td>
    <td>3.035337</td>
    <td>3.015653</td>
   </tr>
   <tr>
    <td>
     <italic>c (Å)</italic>
    </td>
    <td>4.823064</td>
    <td>4.770027</td>
    <td>4.698890</td>
    <td>4.657285</td>
    <td>4.629417</td>
    <td>4.565066</td>
    <td>4.505499</td>
    <td>4.451049</td>
    <td>4.401053</td>
    <td>4.353352</td>
    <td>4.308918</td>
   </tr>
   <tr>
    <td>
     <italic>V (Å</italic>
     <sup>
      <italic>3</italic>
     </sup>
     <italic>)</italic>
    </td>
    <td>124.4219</td>
    <td>122.6337</td>
    <td>120.0533</td>
    <td>118.4413</td>
    <td>117.3462</td>
    <td>114.5878</td>
    <td>111.8689</td>
    <td>109.2402</td>
    <td>106.7016</td>
    <td>104.2052</td>
    <td>101.8082</td>
   </tr>
   <tr>
    <td>
     <italic>V/3 (Å</italic>
     <sup>
      <italic>3</italic>
     </sup>
     <italic>)</italic>
    </td>
    <td>41.4740</td>
    <td>40.8779</td>
    <td>40.0178</td>
    <td>39.4804</td>
    <td>39.1154</td>
    <td>38.1959</td>
    <td>37.2896</td>
    <td>36.4134</td>
    <td>35.5672</td>
    <td>34.7351</td>
    <td>33.9361</td>
   </tr>
   <tr>
    <td>
     <italic>ρ (kg m</italic>
     <sup>
      <italic>−3</italic>
     </sup>
     <italic>)</italic>
    </td>
    <td>2322</td>
    <td>2356</td>
    <td>2406</td>
    <td>2439</td>
    <td>2462</td>
    <td>2521</td>
    <td>2582</td>
    <td>2645</td>
    <td>2707</td>
    <td>2772</td>
    <td>2838</td>
   </tr>
   <tr>
    <td>
     <italic>Mg1 (x/a)</italic>
    </td>
    <td>0.000000</td>
    <td>0.000000</td>
    <td>0.000000</td>
    <td>0.000000</td>
    <td>0.000000</td>
    <td>0.000000</td>
    <td>0.000000</td>
    <td>0.000000</td>
    <td>0.000000</td>
    <td>0.000000</td>
    <td>0.000000</td>
   </tr>
   <tr>
    <td>
     <italic>Mg1 (y/b)</italic>
    </td>
    <td>0.000000</td>
    <td>0.000000</td>
    <td>0.000000</td>
    <td>0.000000</td>
    <td>0.000000</td>
    <td>0.000000</td>
    <td>0.000000</td>
    <td>0.000000</td>
    <td>0.000000</td>
    <td>0.000000</td>
    <td>0.000000</td>
   </tr>
   <tr>
    <td>
     <italic>Mg1 (z/c)</italic>
    </td>
    <td>0.000000</td>
    <td>0.000000</td>
    <td>0.000000</td>
    <td>0.000000</td>
    <td>0.000000</td>
    <td>0.000000</td>
    <td>0.000000</td>
    <td>0.000000</td>
    <td>0.000000</td>
    <td>0.000000</td>
    <td>0.000000</td>
   </tr>
   <tr>
    <td>
     <italic>Mg2 (x/a)</italic>
    </td>
    <td>0.333333</td>
    <td>0.333333</td>
    <td>0.333333</td>
    <td>0.333333</td>
    <td>0.333333</td>
    <td>0.333333</td>
    <td>0.333333</td>
    <td>0.333333</td>
    <td>0.333333</td>
    <td>0.333333</td>
    <td>0.333333</td>
   </tr>
   <tr>
    <td>
     <italic>Mg2 (y/b)</italic>
    </td>
    <td>0.666667</td>
    <td>0.666667</td>
    <td>0.666667</td>
    <td>0.666667</td>
    <td>0.666667</td>
    <td>0.666667</td>
    <td>0.666667</td>
    <td>0.666667</td>
    <td>0.666667</td>
    <td>0.666667</td>
    <td>0.666667</td>
   </tr>
   <tr>
    <td>
     <italic>Mg2 (z/c)</italic>
    </td>
    <td>−0.012533</td>
    <td>−0.013765</td>
    <td>−0.014899</td>
    <td>−0.014865</td>
    <td>−0.014835</td>
    <td>−0.015002</td>
    <td>−0.014868</td>
    <td>−0.014522</td>
    <td>−0.014110</td>
    <td>−0.013815</td>
    <td>−0.013656</td>
   </tr>
   <tr>
    <td>
     <italic>O1 (x/a)</italic>
    </td>
    <td>0.004323</td>
    <td>0.004665</td>
    <td>0.004954</td>
    <td>0.004938</td>
    <td>0.004927</td>
    <td>0.004957</td>
    <td>0.004911</td>
    <td>0.004791</td>
    <td>0.004644</td>
    <td>0.004499</td>
    <td>0.004401</td>
   </tr>
   <tr>
    <td>
     <italic>O1 (y/b)</italic>
    </td>
    <td>0.335505</td>
    <td>0.335673</td>
    <td>0.335822</td>
    <td>0.335816</td>
    <td>0.335814</td>
    <td>0.335855</td>
    <td>0.335813</td>
    <td>0.335756</td>
    <td>0.335675</td>
    <td>0.335611</td>
    <td>0.335585</td>
   </tr>
   <tr>
    <td>
     <italic>O1 (z/c)</italic>
    </td>
    <td>0.217662</td>
    <td>0.220196</td>
    <td>0.223642</td>
    <td>0.225615</td>
    <td>0.226931</td>
    <td>0.230049</td>
    <td>0.232910</td>
    <td>0.235504</td>
    <td>0.237858</td>
    <td>0.240124</td>
    <td>0.242250</td>
   </tr>
   <tr>
    <td>
     <italic>H1 (x/a)</italic>
    </td>
    <td>0.033005</td>
    <td>0.036912</td>
    <td>0.041444</td>
    <td>0.042531</td>
    <td>0.043311</td>
    <td>0.046493</td>
    <td>0.049180</td>
    <td>0.051679</td>
    <td>0.054312</td>
    <td>0.057579</td>
    <td>0.061439</td>
   </tr>
   <tr>
    <td>
     <italic>H1 (y/b)</italic>
    </td>
    <td>0.349532</td>
    <td>0.351391</td>
    <td>0.353461</td>
    <td>0.353991</td>
    <td>0.354371</td>
    <td>0.355728</td>
    <td>0.356838</td>
    <td>0.357857</td>
    <td>0.358915</td>
    <td>0.360210</td>
    <td>0.361716</td>
   </tr>
   <tr>
    <td>
     <italic>H1 (z/c)</italic>
    </td>
    <td>0.415044</td>
    <td>0.419293</td>
    <td>0.425094</td>
    <td>0.428690</td>
    <td>0.431100</td>
    <td>0.436498</td>
    <td>0.441527</td>
    <td>0.446091</td>
    <td>0.450175</td>
    <td>0.453903</td>
    <td>0.457173</td>
   </tr>
  </tbody>
 </table>
</table-wrap>
