<?xml version="1.0" encoding="UTF-8"?>
<table-wrap id="tbl1" position="float">
 <label>Table 1</label>
 <caption>
  <title>Calculated Diagonal Components of the Born Effective Charge Tensors for 
   <italic>x</italic> = 0, 0.5, and 1 of PbTi
   <sub>1–
    <italic>x</italic>
   </sub>V
   <sub>
    <italic>x</italic>
   </sub>O
   <sub>3</sub> in the Ferroelectric Phase with Ground-State Magnetic Ordering
  </title>
 </caption>
 <table frame="hsides" rules="groups" border="0">
  <colgroup>
   <col align="left"/>
   <col align="char" char="."/>
   <col align="char" char="."/>
   <col align="char" char="."/>
   <col align="char" char="."/>
   <col align="char" char="."/>
   <col align="char" char="."/>
   <col align="char" char="."/>
   <col align="char" char="."/>
   <col align="char" char="."/>
  </colgroup>
  <thead>
   <tr>
    <th style="border:none;" align="center">
     <italic>x</italic> →
    </th>
    <th colspan="3" align="center" char=".">0
     <hr/>
    </th>
    <th colspan="3" align="center" char=".">0.5
     <hr/>
    </th>
    <th colspan="3" align="center" char=".">1
     <hr/>
    </th>
   </tr>
   <tr>
    <th style="border:none;" align="center">atom</th>
    <th style="border:none;" align="center" char=".">
     <italic>xx</italic>
    </th>
    <th style="border:none;" align="center" char=".">
     <italic>yy</italic>
    </th>
    <th style="border:none;" align="center" char=".">
     <italic>zz</italic>
    </th>
    <th style="border:none;" align="center" char=".">
     <italic>xx</italic>
    </th>
    <th style="border:none;" align="center" char=".">
     <italic>yy</italic>
    </th>
    <th style="border:none;" align="center" char=".">
     <italic>zz</italic>
    </th>
    <th style="border:none;" align="center" char=".">
     <italic>xx</italic>
    </th>
    <th style="border:none;" align="center" char=".">
     <italic>yy</italic>
    </th>
    <th style="border:none;" align="center" char=".">
     <italic>zz</italic>
    </th>
   </tr>
  </thead>
  <tbody>
   <tr>
    <td style="border:none;" align="left">Pb</td>
    <td style="border:none;" align="char" char=".">3.641</td>
    <td style="border:none;" align="char" char=".">3.641</td>
    <td style="border:none;" align="char" char=".">3.331</td>
    <td style="border:none;" align="char" char=".">3.623</td>
    <td style="border:none;" align="char" char=".">3.617</td>
    <td style="border:none;" align="char" char=".">3.664</td>
    <td style="border:none;" align="char" char=".">3.251</td>
    <td style="border:none;" align="char" char=".">3.232</td>
    <td style="border:none;" align="char" char=".">3.275</td>
   </tr>
   <tr>
    <td style="border:none;" align="left">Ti</td>
    <td style="border:none;" align="char" char=".">6.166</td>
    <td style="border:none;" align="char" char=".">6.166</td>
    <td style="border:none;" align="char" char=".">4.961</td>
    <td style="border:none;" align="char" char=".">5.480</td>
    <td style="border:none;" align="char" char=".">5.406</td>
    <td style="border:none;" align="char" char=".">4.778</td>
    <td style="border:none;" align="char" char="."> </td>
    <td style="border:none;" align="char" char="."> </td>
    <td style="border:none;" align="char" char="."> </td>
   </tr>
   <tr>
    <td style="border:none;" align="left">V</td>
    <td style="border:none;" align="char" char="."> </td>
    <td style="border:none;" align="char" char="."> </td>
    <td style="border:none;" align="char" char="."> </td>
    <td style="border:none;" align="char" char=".">4.348</td>
    <td style="border:none;" align="char" char=".">4.440</td>
    <td style="border:none;" align="char" char=".">4.435</td>
    <td style="border:none;" align="char" char=".">4.880</td>
    <td style="border:none;" align="char" char=".">4.824</td>
    <td style="border:none;" align="char" char=".">3.749</td>
   </tr>
   <tr>
    <td style="border:none;" align="left">O1</td>
    <td style="border:none;" align="char" char=".">–1.938</td>
    <td style="border:none;" align="char" char=".">–1.938</td>
    <td style="border:none;" align="char" char=".">–4.245</td>
    <td style="border:none;" align="char" char=".">–1.148</td>
    <td style="border:none;" align="char" char=".">–1.154</td>
    <td style="border:none;" align="char" char=".">–3.098</td>
    <td style="border:none;" align="char" char=".">–1.442</td>
    <td style="border:none;" align="char" char=".">–1.525</td>
    <td style="border:none;" align="char" char=".">–3.720</td>
   </tr>
   <tr>
    <td style="border:none;" align="left">O2</td>
    <td style="border:none;" align="char" char=".">–2.603</td>
    <td style="border:none;" align="char" char=".">–5.266</td>
    <td style="border:none;" align="char" char=".">–2.024</td>
    <td style="border:none;" align="char" char=".">–2.078</td>
    <td style="border:none;" align="char" char=".">–3.875</td>
    <td style="border:none;" align="char" char=".">–1.417</td>
    <td style="border:none;" align="char" char=".">–2.209</td>
    <td style="border:none;" align="char" char=".">–4.029</td>
    <td style="border:none;" align="char" char=".">–1.764</td>
   </tr>
   <tr>
    <td style="border:none;" align="left">O3</td>
    <td style="border:none;" align="char" char=".">–5.266</td>
    <td style="border:none;" align="char" char=".">–2.603</td>
    <td style="border:none;" align="char" char=".">–2.024</td>
    <td style="border:none;" align="char" char=".">–3.716</td>
    <td style="border:none;" align="char" char=".">–1.899</td>
    <td style="border:none;" align="char" char=".">–1.423</td>
    <td style="border:none;" align="char" char=".">–3.877</td>
    <td style="border:none;" align="char" char=".">–2.513</td>
    <td style="border:none;" align="char" char=".">–1.724</td>
   </tr>
  </tbody>
 </table>
</table-wrap>
