<?xml version="1.0" encoding="UTF-8"?>
<ref id="advs1307-bib-0005">
 <label>5</label>
 <mixed-citation publication-type="journal" id="advs1307-cit-0014">a) 
  <string-name>
   <given-names>G.</given-names>
   <surname>Xing</surname>
  </string-name>, 
  <string-name>
   <given-names>N.</given-names>
   <surname>Mathews</surname>
  </string-name>, 
  <string-name>
   <given-names>S.</given-names>
   <surname>Sun</surname>
  </string-name>, 
  <string-name>
   <given-names>S. S.</given-names>
   <surname>Lim</surname>
  </string-name>, 
  <string-name>
   <given-names>Y. M.</given-names>
   <surname>Lam</surname>
  </string-name>, 
  <string-name>
   <given-names>M.</given-names>
   <surname>Grätzel</surname>
  </string-name>, 
  <string-name>
   <given-names>S.</given-names>
   <surname>Mhaisalkar</surname>
  </string-name>, 
  <string-name>
   <given-names>T. C.</given-names>
   <surname>Sum</surname>
  </string-name>, 
  <source xml:lang="en">Science</source>
  <year>2013</year>, 
  <volume>342</volume>, 
  <fpage>344</fpage>;
  <pub-id pub-id-type="pmid">24136965</pub-id>
 </mixed-citation>
 <mixed-citation publication-type="journal" id="advs1307-cit-0015">b) 
  <string-name>
   <given-names>E.</given-names>
   <surname>Edri</surname>
  </string-name>, 
  <string-name>
   <given-names>S.</given-names>
   <surname>Kirmayer</surname>
  </string-name>, 
  <string-name>
   <given-names>S.</given-names>
   <surname>Mukhopadhyay</surname>
  </string-name>, 
  <string-name>
   <given-names>K.</given-names>
   <surname>Gartsman</surname>
  </string-name>, 
  <string-name>
   <given-names>G.</given-names>
   <surname>Hodes</surname>
  </string-name>, 
  <string-name>
   <given-names>D.</given-names>
   <surname>Cahen</surname>
  </string-name>, 
  <source xml:lang="en">Nat. Commun.</source>
  <year>2014</year>, 
  <volume>5</volume>, 
  <fpage>3461</fpage>;
  <pub-id pub-id-type="pmid">24613942</pub-id>
 </mixed-citation>
 <mixed-citation publication-type="journal" id="advs1307-cit-0016">c) 
  <string-name>
   <given-names>S. D.</given-names>
   <surname>Stranks</surname>
  </string-name>, 
  <string-name>
   <given-names>G. E.</given-names>
   <surname>Eperon</surname>
  </string-name>, 
  <string-name>
   <given-names>G.</given-names>
   <surname>Grancini</surname>
  </string-name>, 
  <string-name>
   <given-names>C.</given-names>
   <surname>Menelaou</surname>
  </string-name>, 
  <string-name>
   <given-names>M. J.</given-names>
   <surname>Alcocer</surname>
  </string-name>, 
  <string-name>
   <given-names>T.</given-names>
   <surname>Leijtens</surname>
  </string-name>, 
  <string-name>
   <given-names>L. M.</given-names>
   <surname>Herz</surname>
  </string-name>, 
  <string-name>
   <given-names>A.</given-names>
   <surname>Petrozza</surname>
  </string-name>, 
  <string-name>
   <given-names>H. J.</given-names>
   <surname>Snaith</surname>
  </string-name>, 
  <source xml:lang="en">Science</source>
  <year>2013</year>, 
  <volume>342</volume>, 
  <fpage>341</fpage>.
  <pub-id pub-id-type="pmid">24136964</pub-id>
 </mixed-citation>
</ref>
