<?xml version="1.0" encoding="UTF-8"?>
<fig id="fig8">
 <label>Fig. 8</label>
 <caption>
  <p>The XRD patterns of the original (1) and after long-term storage (2) sample NCN0.55, which consists of the two PLS compound: Na
   <sub>2</sub>Ca
   <sub>4</sub>Nb
   <sub>6</sub>O
   <sub>20</sub> and Na
   <sub>4</sub>Ca
   <sub>4</sub>Nb
   <sub>8</sub>O
   <sub>26</sub>, formed in the system (1-x) NaNbO
   <sub>3</sub>–xCa
   <sub>2</sub>Nb
   <sub>2</sub>O
   <sub>7</sub> at x = 0.55. On the the XRD pattern 1, the indexes of the diffraction reflections of only Na
   <sub>2</sub>Ca
   <sub>4</sub>Nb
   <sub>6</sub>O
   <sub>20</sub> are shown, and on the XRD pattern 2, only the compounds of Na
   <sub>4</sub>Ca
   <sub>4</sub>Nb
   <sub>8</sub>O
   <sub>26</sub> are shown.
  </p>
 </caption>
 <alt-text id="alttext0045">Fig. 8</alt-text>
 <graphic xlink:href="gr8" xmlns:xlink="http://www.w3.org/1999/xlink"/>
</fig>
