<?xml version="1.0" encoding="UTF-8"?>
<ref id="B50-molecules-24-04387">
 <label>50.</label>
 <element-citation publication-type="book">
  <person-group person-group-type="author">
   <name>
    <surname>Leyendecker</surname>
    <given-names>M.</given-names>
   </name>
  </person-group>
  <source>Supramolecular Lyotropic Liquid Crystalline Alignment Media Based on Benzene-1,3,5-tricarboxamides</source>
  <publisher-name>Technische Universität Darmstadt</publisher-name>
  <publisher-loc>Darmstadt, Germany</publisher-loc>
  <year>2019</year>
 </element-citation>
</ref>
