<?xml version="1.0" encoding="UTF-8"?>
<ref id="R9">
 <label>9</label>
 <mixed-citation publication-type="journal">
  <person-group person-group-type="author">
   <name>
    <surname>Winkler</surname>
    <given-names>C</given-names>
   </name>, 
   <etal>et al</etal>
  </person-group>. 
  <source>J Cell Sci</source>. 
  <year>2015</year>; 
  <volume>128</volume>:
  <fpage>4526</fpage>–
  <lpage>37</lpage>. 
  <pub-id pub-id-type="doi">10.1242/jcs.175588</pub-id>. 
  <?supplied-pmid 26542020?>
  <pub-id pub-id-type="pmid">26542020</pub-id>
 </mixed-citation>
</ref>
