<?xml version="1.0" encoding="UTF-8"?>
<abstract abstract-type="graphical">
 <p>
  <bold>Hydroflux conditions</bold> provide access to oxohydroxoferrates 
  <italic>A</italic>
  <sub>2</sub>[Fe
  <sub>2</sub>O
  <sub>3</sub>(OH)
  <sub>2</sub>] with 
  <italic>A</italic>=K, Rb, Cs. Hydrogen bonds inside and between layers of corner‐sharing [FeO
  <sub>3</sub>OH] tetrahedra strongly influence decomposition temperatures, crystal structures and morphologies. The magnetic moments of the iron(III) cations are aligned antiparallel in neighboring tetrahedra.
  <boxed-text position="anchor" content-type="graphic" orientation="portrait">
   <graphic xlink:href="OPEN-8-1399-g011.jpg" position="anchor" id="nlm-graphic-1" orientation="portrait" xmlns:xlink="http://www.w3.org/1999/xlink"/>
  </boxed-text>
 </p>
</abstract>
