<?xml version="1.0" encoding="UTF-8"?>
<fig id="fig3" position="float">
 <label>Figure 3</label>
 <caption>
  <p>Typical SEM images of GdBO
   <sub>3</sub>:Eu
   <sup>3+</sup> phosphors and the elemental mapping profiles of unannealed precursors synthesized by (a) RPB and (b) conversional STR and annealed products synthesized by (c) RPB route and (d) STR route. The reaction times in the RPB and STR were 2 h and 20 min, respectively.
  </p>
 </caption>
 <graphic xlink:href="ao9b01656_0003" id="gr3" position="float" xmlns:xlink="http://www.w3.org/1999/xlink"/>
</fig>
