<?xml version="1.0" encoding="UTF-8"?>
<fig id="Fig2">
 <label>Figure 2</label>
 <caption>
  <p>(
   <bold>a</bold>) Bright-field transmission electron microscopy and (
   <bold>b</bold>) high-angle annular dark-field (HAADF) scanning transmission electron microscopy images of a polyphased matrix of the metastable phases. (
   <bold>c</bold>) Zoom-in view of the corresponding selected area electron diffraction (SAD) pattern of the 
   <italic>ε</italic>-Al
   <sub>60</sub>Sm
   <sub>11</sub> phase and the unknown phase (designated 
   <italic>η</italic>-Al
   <sub>41</sub>Sm
   <sub>5</sub> later in this work). The zone axis is 
   <inline-formula id="IEq2">
    <alternatives>
     <tex-math id="M3">\documentclass[12pt]{minimal} \usepackage{amsmath} \usepackage{wasysym} \usepackage{amsfonts} \usepackage{amssymb} \usepackage{amsbsy} \usepackage{mathrsfs} \usepackage{upgreek} \setlength{\oddsidemargin}{-69pt} \begin{document}$$[100]$$\end{document}</tex-math>
     <math id="M4">
      <mo stretchy="false">[</mo>
      <mn>100</mn>
      <mo stretchy="false">]</mo>
     </math>
     <inline-graphic xlink:href="41598_2019_43079_Article_IEq2.gif" xmlns:xlink="http://www.w3.org/1999/xlink"/>
    </alternatives>
   </inline-formula> for the 
   <italic>ε</italic>-phase, and is identified later as 
   <inline-formula id="IEq3">
    <alternatives>
     <tex-math id="M5">\documentclass[12pt]{minimal} \usepackage{amsmath} \usepackage{wasysym} \usepackage{amsfonts} \usepackage{amssymb} \usepackage{amsbsy} \usepackage{mathrsfs} \usepackage{upgreek} \setlength{\oddsidemargin}{-69pt} \begin{document}$$[22\bar{1}]$$\end{document}</tex-math>
     <math id="M6">
      <mo stretchy="false">[</mo>
      <mn>22</mn>
      <mover accent="true">
       <mn>1</mn>
       <mo>¯</mo>
      </mover>
      <mo stretchy="false">]</mo>
     </math>
     <inline-graphic xlink:href="41598_2019_43079_Article_IEq3.gif" xmlns:xlink="http://www.w3.org/1999/xlink"/>
    </alternatives>
   </inline-formula> for the 
   <italic>η</italic>-phase. (
   <bold>d</bold>) the SAD pattern that shows diffraction rings from nanocrystalline fcc-Al grains.
  </p>
 </caption>
 <graphic xlink:href="41598_2019_43079_Fig2_HTML" id="d29e730" xmlns:xlink="http://www.w3.org/1999/xlink"/>
</fig>
