<?xml version="1.0" encoding="UTF-8"?>
<ref id="anie201909240-bib-0014b">
 <label>14b</label>
 <mixed-citation publication-type="journal" id="anie201909240-cit-0049">
  <string-name>
   <given-names>C.</given-names>
   <surname>Müller</surname>
  </string-name>, 
  <string-name>
   <given-names>L. E. E.</given-names>
   <surname>Broeckx</surname>
  </string-name>, 
  <string-name>
   <given-names>I.</given-names>
   <surname>de Krom</surname>
  </string-name>, 
  <string-name>
   <given-names>J. J. M.</given-names>
   <surname>Weemers</surname>
  </string-name>, 
  <source xml:lang="en">Eur. J. Inorg. Chem.</source>
  <year>2013</year>, 
  <fpage>187</fpage>–
  <lpage>202</lpage>.
 </mixed-citation>
</ref>
